colcon_gradle/__init__.py
colcon_gradle/argcomplete_completer/__init__.py
colcon_gradle/argcomplete_completer/gradle_args.py
colcon_gradle/environment/__init__.py
colcon_gradle/package_identification/__init__.py
colcon_gradle/package_identification/gradle.py
colcon_gradle/task/__init__.py
colcon_gradle/task/gradle/__init__.py
colcon_gradle/task/gradle/build.py
colcon_gradle/task/gradle/test.py
colcon_gradle-0.1.1.dist-info/LICENSE
colcon_gradle-0.1.1.dist-info/METADATA
colcon_gradle-0.1.1.dist-info/WHEEL
colcon_gradle-0.1.1.dist-info/entry_points.txt
colcon_gradle-0.1.1.dist-info/top_level.txt
colcon_gradle-0.1.1.dist-info/zip-safe
colcon_gradle-0.1.1.dist-info/RECORD
