Metadata-Version: 2.1
Name: colcon-gradle
Version: 0.1.1
Summary: Extension for colcon to support Gradle packages.
Home-page: https://colcon.readthedocs.io
Author: Esteve Fernandez
Author-email: esteve@apache.org
Maintainer: Esteve Fernandez, Jacob Perron
Maintainer-email: esteve@apache.org,jacob@openrobotics.org
License: Apache License, Version 2.0
Project-URL: Changelog, https://github.com/colcon/colcon-gradle/milestones?state=closed
Project-URL: GitHub, https://github.com/colcon/colcon-gradle/
Keywords: colcon
Classifier: Development Status :: 3 - Alpha
Classifier: Environment :: Plugins
Classifier: Intended Audience :: Developers
Classifier: License :: OSI Approved :: Apache Software License
Classifier: Operating System :: MacOS
Classifier: Operating System :: Microsoft :: Windows
Classifier: Operating System :: POSIX
Classifier: Programming Language :: Python
Classifier: Topic :: Software Development :: Build Tools
License-File: LICENSE
Requires-Dist: colcon-core
Requires-Dist: colcon-library-path
Provides-Extra: test
Requires-Dist: flake8 ; extra == 'test'
Requires-Dist: flake8-blind-except ; extra == 'test'
Requires-Dist: flake8-builtins ; extra == 'test'
Requires-Dist: flake8-class-newline ; extra == 'test'
Requires-Dist: flake8-comprehensions ; extra == 'test'
Requires-Dist: flake8-deprecated ; extra == 'test'
Requires-Dist: flake8-docstrings ; extra == 'test'
Requires-Dist: flake8-import-order ; extra == 'test'
Requires-Dist: flake8-quotes ; extra == 'test'
Requires-Dist: pep8-naming ; extra == 'test'
Requires-Dist: pyenchant ; extra == 'test'
Requires-Dist: pylint ; extra == 'test'
Requires-Dist: pytest ; extra == 'test'
Requires-Dist: pytest-cov ; extra == 'test'
